tezzcrawler/__init__.py
tezzcrawler/cli/__init__.py
tezzcrawler/cli/commands.py
tezzcrawler/core/__init__.py
tezzcrawler/core/crawler.py
tezzcrawler/core/scraper.py
tezzcrawler/utils/__init__.py
tezzcrawler/utils/headers.py
tezzcrawler/utils/proxy.py
TezzCrawler-0.3.1.dist-info/LICENSE
TezzCrawler-0.3.1.dist-info/METADATA
TezzCrawler-0.3.1.dist-info/WHEEL
TezzCrawler-0.3.1.dist-info/entry_points.txt
TezzCrawler-0.3.1.dist-info/top_level.txt
TezzCrawler-0.3.1.dist-info/RECORD
