Metadata-Version: 2.1
Name: TezzCrawler
Version: 0.3.1
Summary: A web crawler that converts web pages to markdown and prepares them for LLM consumption
Home-page: https://github.com/TezzLabs/TezzCrawler
Author: Japkeerat Singh
Author-email: japkeerat21@gmail.com
Classifier: Programming Language :: Python :: 3
Classifier: License :: OSI Approved :: MIT License
Classifier: Operating System :: OS Independent
Requires-Python: >=3.10
License-File: LICENSE
Requires-Dist: requests==2.32.3
Requires-Dist: typer==0.13.0
Requires-Dist: beautifulsoup4==4.12.3
Requires-Dist: markdownify==0.13.1
Requires-Dist: lxml==5.3.0
